luntaiDs/__init__.py
luntaiDs/CommonTools/__init__.py
luntaiDs/CommonTools/accessor.py
luntaiDs/CommonTools/data_structure.py
luntaiDs/CommonTools/dbapi.py
luntaiDs/CommonTools/dtyper.py
luntaiDs/CommonTools/login.py
luntaiDs/CommonTools/obj_storage.py
luntaiDs/CommonTools/schema_manager.py
luntaiDs/CommonTools/settings.py
luntaiDs/CommonTools/sparker.py
luntaiDs/CommonTools/utils.py
luntaiDs/CommonTools/warehouse.py
luntaiDs/CommonTools/SnapStructure/__init__.py
luntaiDs/CommonTools/SnapStructure/dependency.py
luntaiDs/CommonTools/SnapStructure/structure.py
luntaiDs/CommonTools/SnapStructure/tools.py
luntaiDs/ModelingTools/__init__.py
luntaiDs/ModelingTools/CustomModel/__init__.py
luntaiDs/ModelingTools/CustomModel/calibration.py
luntaiDs/ModelingTools/CustomModel/custom.py
luntaiDs/ModelingTools/CustomModel/linear.py
luntaiDs/ModelingTools/CustomModel/ordinal.py
luntaiDs/ModelingTools/CustomModel/sampler.py
luntaiDs/ModelingTools/CustomModel/splitter.py
luntaiDs/ModelingTools/Evaluation/__init__.py
luntaiDs/ModelingTools/Evaluation/metrics.py
luntaiDs/ModelingTools/Evaluation/plots.py
luntaiDs/ModelingTools/Evaluation/validator.py
luntaiDs/ModelingTools/Explore/__init__.py
luntaiDs/ModelingTools/Explore/plots.py
luntaiDs/ModelingTools/Explore/summary.py
luntaiDs/ModelingTools/Explore/engines/__init__.py
luntaiDs/ModelingTools/Explore/engines/base.py
luntaiDs/ModelingTools/Explore/engines/ibis.py
luntaiDs/ModelingTools/Explore/engines/pandas.py
luntaiDs/ModelingTools/FeatureEngineer/__init__.py
luntaiDs/ModelingTools/FeatureEngineer/featureHelper.py
luntaiDs/ModelingTools/FeatureEngineer/feature_selection.py
luntaiDs/ModelingTools/FeatureEngineer/preprocessing.py
luntaiDs/ModelingTools/FeatureEngineer/transformers.py
luntaiDs/ModelingTools/Serving/__init__.py
luntaiDs/ModelingTools/Serving/data_registry.py
luntaiDs/ModelingTools/Serving/model_registry.py
luntaiDs/ModelingTools/Serving/timetable.py
luntaiDs/ModelingTools/utils/__init__.py
luntaiDs-1.0.42.dist-info/LICENSE
luntaiDs-1.0.42.dist-info/METADATA
luntaiDs-1.0.42.dist-info/WHEEL
luntaiDs-1.0.42.dist-info/top_level.txt
luntaiDs-1.0.42.dist-info/RECORD
