Metadata-Version: 2.1
Name: luntaiDs
Version: 1.0.42
Summary: Make Data Scientist life Easier Tool
Home-page: https://github.com/luntaixiax/luntai-ds
Author: Ailun Qian (luntaixia)
Author-email: ailunqian124@gmail.com
License: MIT License
Requires-Python: >=3.8
License-File: LICENSE
Requires-Dist: dacite==1.8.1
Requires-Dist: requests==2.28.1
Requires-Dist: sqlalchemy==1.4.45
Requires-Dist: clickhouse-connect==0.7.1
Requires-Dist: mysql-connector-python==8.3.0
Requires-Dist: pymongo==4.6.2
Requires-Dist: teradata==15.10.0.21
Requires-Dist: teradatasql==17.20.0.0
Requires-Dist: teradatasqlalchemy==17.0.0.3
Requires-Dist: tqdm==4.64.1
Requires-Dist: feast==0.39.1
Requires-Dist: pyarrow==15.0
Requires-Dist: fsspec==2024.6.1
Requires-Dist: universal-pathlib==0.2.2
Requires-Dist: s3fs==2024.6.1
Requires-Dist: gcsfs==2024.6.1
Requires-Dist: pandas==2.2.2
Requires-Dist: pyspark==3.3.4
Requires-Dist: ortools==9.4.1874
Requires-Dist: google-api-python-client==2.115.0
Requires-Dist: google-auth-httplib2==0.2.0
Requires-Dist: google-auth-oauthlib==1.2.0
Requires-Dist: google-cloud-storage==2.14.0
Requires-Dist: pybigquery==0.5.0
Requires-Dist: ibis-framework==9.3.0
Requires-Dist: ibis-framework[bigquery,clickhouse,duckdb,pandas,polars,postgres,pyspark,snowflake,sqlite]
Requires-Dist: openpyxl==3.1.2
Requires-Dist: scikit-learn==1.0.2
Requires-Dist: imbalanced-learn==0.10.1
Requires-Dist: mlxtend==0.21.0
Requires-Dist: category-encoders==2.6.2
Requires-Dist: lightgbm==4.0.0
Requires-Dist: optbinning==0.17.3
Requires-Dist: scikit-optimize==0.9.0
Requires-Dist: optuna==3.6.1
Requires-Dist: optuna-integration==3.6.0
Requires-Dist: optuna-dashboard==0.15.1
Requires-Dist: shap==0.46.0
Requires-Dist: email-validator==2.2.0
Requires-Dist: joblib==1.4.2
Requires-Dist: uvicorn==0.30.5
Requires-Dist: fastapi==0.112.0
Requires-Dist: bokeh==2.4.3
Requires-Dist: toml==0.10.2
Requires-Dist: mlflow==2.15.1
